ultyas/__init__.py
ultyas/ultisnips.py
ultyas-1.1.0.dist-info/LICENSE
ultyas-1.1.0.dist-info/METADATA
ultyas-1.1.0.dist-info/WHEEL
ultyas-1.1.0.dist-info/entry_points.txt
ultyas-1.1.0.dist-info/top_level.txt
ultyas-1.1.0.dist-info/RECORD
