Metadata-Version: 2.1
Name: ultyas
Version: 1.1.0
Summary: A tool for converting code snippets from Ultisnips to YASnippet format
Home-page: https://github.com/jamescherti/ultyas
Author: James Cherti
Classifier: Development Status :: 5 - Production/Stable
Classifier: License :: OSI Approved :: GNU General Public License (GPL)
Classifier: License :: OSI Approved :: GNU General Public License v3 (GPLv3)
Classifier: Environment :: Console
Classifier: Operating System :: POSIX :: Linux
Classifier: Operating System :: POSIX :: Other
Classifier: Topic :: Text Editors :: Emacs
Classifier: Programming Language :: Python :: 3
Requires-Python: >=3.6, <4
License-File: LICENSE
